komodo_mlipir_algorithm-1.0.2.dist-info/licenses/LICENSE
optimizer/__init__.py
optimizer/__version__.py
optimizer/cli.py
optimizer/py.typed
optimizer/algorithm/__init__.py
optimizer/algorithm/komodo_mlipir_algorithm.py
optimizer/utils/__init__.py
optimizer/utils/benchmark.py
optimizer/utils/visualization.py
komodo_mlipir_algorithm-1.0.2.dist-info/METADATA
komodo_mlipir_algorithm-1.0.2.dist-info/WHEEL
komodo_mlipir_algorithm-1.0.2.dist-info/entry_points.txt
komodo_mlipir_algorithm-1.0.2.dist-info/top_level.txt
komodo_mlipir_algorithm-1.0.2.dist-info/RECORD
