Metadata-Version: 2.4
Name: komodo-mlipir-algorithm
Version: 1.0.2
Summary: A Python implementation of Komodo Mlipir Algorithm (KMA) for optimization
Home-page: https://github.com/khalifardy/komodo_mlipir_algorithm
Author: Pejalan Sunyi
Author-email: Pejalan Sunyi <khalifardy.miqdarsah@gmail.com>
Maintainer-email: Pejalan Sunyi <khalifardy.miqdarsah@gmail.com>
License: # LICENSE
Project-URL: Homepage, https://github.com/khalifardy/komodo_mlipir_algorithm
Project-URL: Documentation, https://komodo-mlipir-algorithm.readthedocs.io/
Project-URL: Repository, https://github.com/khalifardy/komodo_mlipir_algorithm
Project-URL: Bug Tracker, https://github.com/khalifardy/komodo_mlipir_algorithm/issues
Project-URL: Changelog, https://github.com/khalifardy/komodo_mlipir_algorithm/blob/main/CHANGELOG.md
Keywords: optimization,metaheuristic,komodo-mlipir,evolutionary-algorithm,swarm-intelligence,nature-inspired,global-optimization
Classifier: Development Status :: 4 - Beta
Classifier: Intended Audience :: Developers
Classifier: Intended Audience :: Science/Research
Classifier: License :: OSI Approved :: MIT License
Classifier: Operating System :: OS Independent
Classifier: Programming Language :: Python :: 3
Classifier: Programming Language :: Python :: 3.8
Classifier: Programming Language :: Python :: 3.9
Classifier: Programming Language :: Python :: 3.10
Classifier: Programming Language :: Python :: 3.11
Classifier: Programming Language :: Python :: 3.12
Classifier: Topic :: Scientific/Engineering :: Artificial Intelligence
Classifier: Topic :: Scientific/Engineering :: Mathematics
Classifier: Topic :: Software Development :: Libraries :: Python Modules
Classifier: Typing :: Typed
Requires-Python: >=3.8
License-File: LICENSE
Requires-Dist: numpy>=1.20.0
Provides-Extra: dev
Requires-Dist: pytest>=6.0.0; extra == "dev"
Requires-Dist: pytest-cov>=2.12.0; extra == "dev"
Requires-Dist: pytest-mock>=3.6.0; extra == "dev"
Requires-Dist: black>=21.6b0; extra == "dev"
Requires-Dist: flake8>=3.9.0; extra == "dev"
Requires-Dist: mypy>=0.910; extra == "dev"
Requires-Dist: isort>=5.9.0; extra == "dev"
Requires-Dist: pre-commit>=2.15.0; extra == "dev"
Provides-Extra: docs
Requires-Dist: sphinx>=4.0.0; extra == "docs"
Requires-Dist: sphinx-rtd-theme>=0.5.0; extra == "docs"
Requires-Dist: sphinx-autodoc-typehints>=1.12.0; extra == "docs"
Provides-Extra: viz
Requires-Dist: matplotlib>=3.3.0; extra == "viz"
Requires-Dist: seaborn>=0.11.0; extra == "viz"
Requires-Dist: plotly>=5.0.0; extra == "viz"
Provides-Extra: examples
Requires-Dist: jupyter>=1.0.0; extra == "examples"
Requires-Dist: notebook>=6.4.0; extra == "examples"
Requires-Dist: ipykernel>=6.0.0; extra == "examples"
Provides-Extra: all
Requires-Dist: komodo-mlipir-algorithm[dev,docs,examples,viz]; extra == "all"
Dynamic: author
Dynamic: home-page
Dynamic: license-file
Dynamic: requires-python
